data_karkhana/Downloader.py
data_karkhana/Peer.py
data_karkhana/Tracker.py
data_karkhana/Uploader.py
data_karkhana/__init__.py
data_karkhana/main.py
data_karkhana/setup.py
datakarkhana-0.1.0.dist-info/LICENSE
datakarkhana-0.1.0.dist-info/METADATA
datakarkhana-0.1.0.dist-info/WHEEL
datakarkhana-0.1.0.dist-info/entry_points.txt
datakarkhana-0.1.0.dist-info/top_level.txt
datakarkhana-0.1.0.dist-info/RECORD
